HunterRockWebsocket/HunterRockWebsocket.py
HunterRockWebsocket/Message.py
HunterRockWebsocket/__init__.py
HunterRockWebsocket/__version__.py
HunterRockWebsocket-1.0.6.dist-info/LICENSE
HunterRockWebsocket-1.0.6.dist-info/METADATA
HunterRockWebsocket-1.0.6.dist-info/WHEEL
HunterRockWebsocket-1.0.6.dist-info/top_level.txt
HunterRockWebsocket-1.0.6.dist-info/RECORD
