Metadata-Version: 2.1
Name: HunterRockWebsocket
Version: 1.0.6
Summary: HunterRockWebsocket
Home-page: https://github.com/hunterrockmedya/HunterRockWebsocket
Author: HunterRock
Author-email: hunterrockmedya@gmail.com
License: MIT
Platform: UNKNOWN
Classifier: License :: OSI Approved :: MIT License
Classifier: Programming Language :: Python
Classifier: Programming Language :: Python :: 3
Classifier: Programming Language :: Python :: 3.6
Classifier: Programming Language :: Python :: Implementation :: CPython
Classifier: Programming Language :: Python :: Implementation :: PyPy
Requires-Python: >=3.6.0
